runschema/__init__.py
runschema/calculation.py
runschema/method.py
runschema/nomad_plugin.yaml
runschema/run.py
runschema/system.py
nomad_schema_plugin_run-1.0.4.dist-info/LICENSE
nomad_schema_plugin_run-1.0.4.dist-info/METADATA
nomad_schema_plugin_run-1.0.4.dist-info/WHEEL
nomad_schema_plugin_run-1.0.4.dist-info/entry_points.txt
nomad_schema_plugin_run-1.0.4.dist-info/top_level.txt
nomad_schema_plugin_run-1.0.4.dist-info/RECORD
