Metadata-Version: 2.1
Name: nomad-schema-plugin-run
Version: 1.0.4
Summary: Run schema plugin for NOMAD.
Author: The NOMAD Authors
License: Apache-2.0
Project-URL: homepage, https://github.com/nomad-coe/nomad-schema-plugin-run.git
License-File: LICENSE
Requires-Dist: nomad-lab>=1.3.6.dev1
Provides-Extra: dev
Requires-Dist: mypy==1.0.1; extra == "dev"
Requires-Dist: pytest<8,>=5.3.0; extra == "dev"
Requires-Dist: pytest-timeout>=1.4.2; extra == "dev"
Requires-Dist: pytest-cov>=2.7.1; extra == "dev"
Requires-Dist: ruff>=0.6; extra == "dev"
Requires-Dist: typing-extensions>=4.12; extra == "dev"
